<measures-document><measures speechEventID="FOLK_E_00001_SE_01"><measure type="articulationRate" articulationRate="5.027032198299946"/></measures><measures speechEventID="FOLK_E_00002_SE_01"><measure type="articulationRate" articulationRate="4.324335673812818"/></measures><measures speechEventID="FOLK_E_00003_SE_01"><measure type="articulationRate" articulationRate="5.214132789143376"/></measures><measures speechEventID="FOLK_E_00004_SE_01"><measure type="articulationRate" articulationRate="5.7483374013232735"/></measures><measures speechEventID="FOLK_E_00005_SE_01"><measure type="articulationRate" articulationRate="5.458469022592421"/></measures><measures speechEventID="FOLK_E_00006_SE_01"><measure type="articulationRate" articulationRate="5.344316318021176"/></measures><measures speechEventID="FOLK_E_00007_SE_01"><measure type="articulationRate" articulationRate="5.57798565233066"/></measures><measures speechEventID="FOLK_E_00008_SE_01"><measure type="articulationRate" articulationRate="5.223570401709274"/></measures><measures speechEventID="FOLK_E_00009_SE_01"><measure type="articulationRate" articulationRate="4.988031781420004"/></measures><measures speechEventID="FOLK_E_00010_SE_01"><measure type="articulationRate" articulationRate="4.402335151689168"/></measures><measures speechEventID="FOLK_E_00011_SE_01"><measure type="articulationRate" articulationRate="3.949339604365452"/></measures><measures speechEventID="FOLK_E_00012_SE_01"><measure type="articulationRate" articulationRate="4.278025302712332"/></measures><measures speechEventID="FOLK_E_00013_SE_01"><measure type="articulationRate" articulationRate="3.7394588495487078"/></measures><measures speechEventID="FOLK_E_00014_SE_01"><measure type="articulationRate" articulationRate="3.514533135971933"/></measures><measures speechEventID="FOLK_E_00015_SE_01"><measure type="articulationRate" articulationRate="5.125416287691115"/></measures><measures speechEventID="FOLK_E_00016_SE_01"><measure type="articulationRate" articulationRate="3.815821737537726"/></measures><measures speechEventID="FOLK_E_00017_SE_01"><measure type="articulationRate" articulationRate="3.718603372872041"/></measures><measures speechEventID="FOLK_E_00018_SE_01"><measure type="articulationRate" articulationRate="5.770669913415733"/></measures><measures speechEventID="FOLK_E_00020_SE_01"><measure type="articulationRate" articulationRate="5.43010105756137"/></measures><measures speechEventID="FOLK_E_00021_SE_01"><measure type="articulationRate" articulationRate="5.128193183682297"/></measures><measures speechEventID="FOLK_E_00022_SE_01"><measure type="articulationRate" articulationRate="5.099587576102908"/></measures><measures speechEventID="FOLK_E_00024_SE_01"><measure type="articulationRate" articulationRate="5.334728045733853"/></measures><measures speechEventID="FOLK_E_00026_SE_01"><measure type="articulationRate" articulationRate="5.283847098287256"/></measures><measures speechEventID="FOLK_E_00027_SE_01"><measure type="articulationRate" articulationRate="4.851838036926605"/></measures><measures speechEventID="FOLK_E_00028_SE_01"><measure type="articulationRate" articulationRate="3.9256546892520916"/></measures><measures speechEventID="FOLK_E_00029_SE_01"><measure type="articulationRate" articulationRate="4.300956366244773"/></measures><measures speechEventID="FOLK_E_00030_SE_01"><measure type="articulationRate" articulationRate="4.298024329593322"/></measures><measures speechEventID="FOLK_E_00031_SE_01"><measure type="articulationRate" articulationRate="4.341825060536172"/></measures><measures speechEventID="FOLK_E_00032_SE_01"><measure type="articulationRate" articulationRate="4.634195961629238"/></measures><measures speechEventID="FOLK_E_00033_SE_01"><measure type="articulationRate" articulationRate="5.007766054308835"/></measures><measures speechEventID="FOLK_E_00034_SE_01"><measure type="articulationRate" articulationRate="5.0340439637260035"/></measures><measures speechEventID="FOLK_E_00035_SE_01"><measure type="articulationRate" articulationRate="4.825258695227747"/></measures><measures speechEventID="FOLK_E_00036_SE_01"><measure type="articulationRate" articulationRate="5.0110626910978535"/></measures><measures speechEventID="FOLK_E_00037_SE_01"><measure type="articulationRate" articulationRate="4.702282596457272"/></measures><measures speechEventID="FOLK_E_00038_SE_01"><measure type="articulationRate" articulationRate="4.594180704441045"/></measures><measures speechEventID="FOLK_E_00039_SE_01"><measure type="articulationRate" articulationRate="5.692814255277976"/></measures><measures speechEventID="FOLK_E_00040_SE_01"><measure type="articulationRate" articulationRate="4.986016619217686"/></measures><measures speechEventID="FOLK_E_00042_SE_01"><measure type="articulationRate" articulationRate="5.990831084616368"/></measures><measures speechEventID="FOLK_E_00043_SE_01"><measure type="articulationRate" articulationRate="4.8918169504506706"/></measures><measures speechEventID="FOLK_E_00044_SE_01"><measure type="articulationRate" articulationRate="5.870564946650279"/></measures><measures speechEventID="FOLK_E_00045_SE_01"><measure type="articulationRate" articulationRate="5.9599820041717795"/></measures><measures speechEventID="FOLK_E_00046_SE_01"><measure type="articulationRate" articulationRate="5.925412360329582"/></measures><measures speechEventID="FOLK_E_00047_SE_01"><measure type="articulationRate" articulationRate="5.194426345842898"/></measures><measures speechEventID="FOLK_E_00048_SE_01"><measure type="articulationRate" articulationRate="5.161343588053206"/></measures><measures speechEventID="FOLK_E_00049_SE_01"><measure type="articulationRate" articulationRate="5.8222695551799655"/></measures><measures speechEventID="FOLK_E_00050_SE_01"><measure type="articulationRate" articulationRate="4.897270800003151"/></measures><measures speechEventID="FOLK_E_00052_SE_01"><measure type="articulationRate" articulationRate="4.621792648893063"/></measures><measures speechEventID="FOLK_E_00053_SE_01"><measure type="articulationRate" articulationRate="5.1952884601623035"/></measures><measures speechEventID="FOLK_E_00055_SE_01"><measure type="articulationRate" articulationRate="5.379346150110659"/></measures><measures speechEventID="FOLK_E_00056_SE_01"><measure type="articulationRate" articulationRate="4.861320872052744"/></measures><measures speechEventID="FOLK_E_00057_SE_01"><measure type="articulationRate" articulationRate="4.763943868228281"/></measures><measures speechEventID="FOLK_E_00058_SE_01"><measure type="articulationRate" articulationRate="5.1270877074026275"/></measures><measures speechEventID="FOLK_E_00059_SE_01"><measure type="articulationRate" articulationRate="4.774547804834847"/></measures><measures speechEventID="FOLK_E_00060_SE_01"><measure type="articulationRate" articulationRate="4.632449394404027"/></measures><measures speechEventID="FOLK_E_00061_SE_01"><measure type="articulationRate" articulationRate="5.162422853030696"/></measures><measures speechEventID="FOLK_E_00062_SE_01"><measure type="articulationRate" articulationRate="4.642171350537248"/></measures><measures speechEventID="FOLK_E_00064_SE_01"><measure type="articulationRate" articulationRate="4.959374298903074"/></measures><measures speechEventID="FOLK_E_00066_SE_01"><measure type="articulationRate" articulationRate="5.474597570630722"/></measures><measures speechEventID="FOLK_E_00068_SE_01"><measure type="articulationRate" articulationRate="4.941313264035367"/></measures><measures speechEventID="FOLK_E_00069_SE_01"><measure type="articulationRate" articulationRate="5.023592137125902"/></measures><measures speechEventID="FOLK_E_00070_SE_01"><measure type="articulationRate" articulationRate="5.029706592411358"/></measures><measures speechEventID="FOLK_E_00074_SE_01"><measure type="articulationRate" articulationRate="3.9334617562888123"/></measures><measures speechEventID="FOLK_E_00076_SE_01"><measure type="articulationRate" articulationRate="3.3868495169283057"/></measures><measures speechEventID="FOLK_E_00077_SE_01"><measure type="articulationRate" articulationRate="6.279978975524289"/></measures><measures speechEventID="FOLK_E_00079_SE_01"><measure type="articulationRate" articulationRate="5.36823050696653"/></measures><measures speechEventID="FOLK_E_00080_SE_01"><measure type="articulationRate" articulationRate="4.275544195166026"/></measures><measures speechEventID="FOLK_E_00081_SE_01"><measure type="articulationRate" articulationRate="4.981866007731856"/></measures><measures speechEventID="FOLK_E_00082_SE_01"><measure type="articulationRate" articulationRate="5.043634536962209"/></measures><measures speechEventID="FOLK_E_00083_SE_01"><measure type="articulationRate" articulationRate="5.1394762538233225"/></measures><measures speechEventID="FOLK_E_00084_SE_01"><measure type="articulationRate" articulationRate="5.39288346738592"/></measures><measures speechEventID="FOLK_E_00085_SE_01"><measure type="articulationRate" articulationRate="5.162140640874266"/></measures><measures speechEventID="FOLK_E_00086_SE_01"><measure type="articulationRate" articulationRate="4.83063933900208"/></measures><measures speechEventID="FOLK_E_00087_SE_01"><measure type="articulationRate" articulationRate="4.656888216764793"/></measures><measures speechEventID="FOLK_E_00088_SE_01"><measure type="articulationRate" articulationRate="5.124800819420629"/></measures><measures speechEventID="FOLK_E_00089_SE_01"><measure type="articulationRate" articulationRate="4.937633519399087"/></measures><measures speechEventID="FOLK_E_00090_SE_01"><measure type="articulationRate" articulationRate="4.54255454893455"/></measures><measures speechEventID="FOLK_E_00091_SE_01"><measure type="articulationRate" articulationRate="5.653351941602024"/></measures><measures speechEventID="FOLK_E_00092_SE_01"><measure type="articulationRate" articulationRate="6.154591842169738"/></measures><measures speechEventID="FOLK_E_00093_SE_01"><measure type="articulationRate" articulationRate="4.4731924617494645"/></measures><measures speechEventID="FOLK_E_00094_SE_01"><measure type="articulationRate" articulationRate="4.884115319389486"/></measures><measures speechEventID="FOLK_E_00095_SE_01"><measure type="articulationRate" articulationRate="5.256176284066138"/></measures><measures speechEventID="FOLK_E_00096_SE_01"><measure type="articulationRate" articulationRate="4.080621610346263"/></measures><measures speechEventID="FOLK_E_00097_SE_01"><measure type="articulationRate" articulationRate="4.036970872726217"/></measures><measures speechEventID="FOLK_E_00098_SE_01"><measure type="articulationRate" articulationRate="4.216811774601265"/></measures><measures speechEventID="FOLK_E_00099_SE_01"><measure type="articulationRate" articulationRate="5.474563064463394"/></measures><measures speechEventID="FOLK_E_00100_SE_01"><measure type="articulationRate" articulationRate="4.5564430890439995"/></measures><measures speechEventID="FOLK_E_00101_SE_01"><measure type="articulationRate" articulationRate="4.871677702545368"/></measures><measures speechEventID="FOLK_E_00102_SE_01"><measure type="articulationRate" articulationRate="5.428887613513726"/></measures><measures speechEventID="FOLK_E_00103_SE_01"><measure type="articulationRate" articulationRate="4.3076327721876755"/></measures><measures speechEventID="FOLK_E_00104_SE_01"><measure type="articulationRate" articulationRate="4.949933974522862"/></measures><measures speechEventID="FOLK_E_00105_SE_01"><measure type="articulationRate" articulationRate="4.716060799632246"/></measures><measures speechEventID="FOLK_E_00106_SE_01"><measure type="articulationRate" articulationRate="4.556005782818514"/></measures><measures speechEventID="FOLK_E_00107_SE_01"><measure type="articulationRate" articulationRate="4.201974928216258"/></measures><measures speechEventID="FOLK_E_00108_SE_01"><measure type="articulationRate" articulationRate="4.234992177182318"/></measures><measures speechEventID="FOLK_E_00109_SE_01"><measure type="articulationRate" articulationRate="4.938109496598887"/></measures><measures speechEventID="FOLK_E_00110_SE_01"><measure type="articulationRate" articulationRate="4.718944591918789"/></measures><measures speechEventID="FOLK_E_00111_SE_01"><measure type="articulationRate" articulationRate="4.373446002480465"/></measures><measures speechEventID="FOLK_E_00112_SE_01"><measure type="articulationRate" articulationRate="4.989406682503145"/></measures><measures speechEventID="FOLK_E_00113_SE_01"><measure type="articulationRate" articulationRate="4.145574847765527"/></measures><measures speechEventID="FOLK_E_00114_SE_01"><measure type="articulationRate" articulationRate="4.827071776038706"/></measures><measures speechEventID="FOLK_E_00115_SE_01"><measure type="articulationRate" articulationRate="4.106844666994272"/></measures><measures speechEventID="FOLK_E_00116_SE_01"><measure type="articulationRate" articulationRate="4.29625002390347"/></measures><measures speechEventID="FOLK_E_00117_SE_01"><measure type="articulationRate" articulationRate="4.697339020922207"/></measures><measures speechEventID="FOLK_E_00118_SE_01"><measure type="articulationRate" articulationRate="4.620327017186991"/></measures><measures speechEventID="FOLK_E_00119_SE_01"><measure type="articulationRate" articulationRate="4.380606862374751"/></measures><measures speechEventID="FOLK_E_00120_SE_01"><measure type="articulationRate" articulationRate="5.32432872084639"/></measures><measures speechEventID="FOLK_E_00121_SE_01"><measure type="articulationRate" articulationRate="5.386966759708125"/></measures><measures speechEventID="FOLK_E_00123_SE_01"><measure type="articulationRate" articulationRate="4.529055039533291"/></measures><measures speechEventID="FOLK_E_00124_SE_01"><measure type="articulationRate" articulationRate="5.181813028614355"/></measures><measures speechEventID="FOLK_E_00125_SE_01"><measure type="articulationRate" articulationRate="5.222828459915537"/></measures><measures speechEventID="FOLK_E_00126_SE_01"><measure type="articulationRate" articulationRate="5.310002749698074"/></measures><measures speechEventID="FOLK_E_00127_SE_01"><measure type="articulationRate" articulationRate="4.986627605877704"/></measures><measures speechEventID="FOLK_E_00128_SE_01"><measure type="articulationRate" articulationRate="5.519538576847433"/></measures><measures speechEventID="FOLK_E_00129_SE_01"><measure type="articulationRate" articulationRate="4.956268977776558"/></measures><measures speechEventID="FOLK_E_00130_SE_01"><measure type="articulationRate" articulationRate="4.706931991048105"/></measures><measures speechEventID="FOLK_E_00132_SE_01"><measure type="articulationRate" articulationRate="4.867694941327516"/></measures><measures speechEventID="FOLK_E_00133_SE_01"><measure type="articulationRate" articulationRate="5.484099378577656"/></measures><measures speechEventID="FOLK_E_00134_SE_01"><measure type="articulationRate" articulationRate="5.618731716048494"/></measures><measures speechEventID="FOLK_E_00135_SE_01"><measure type="articulationRate" articulationRate="5.435411125245747"/></measures><measures speechEventID="FOLK_E_00136_SE_01"><measure type="articulationRate" articulationRate="5.063906677185127"/></measures><measures speechEventID="FOLK_E_00137_SE_01"><measure type="articulationRate" articulationRate="4.564503797046298"/></measures><measures speechEventID="FOLK_E_00138_SE_01"><measure type="articulationRate" articulationRate="6.404466532513853"/></measures><measures speechEventID="FOLK_E_00139_SE_01"><measure type="articulationRate" articulationRate="4.70042842072781"/></measures><measures speechEventID="FOLK_E_00140_SE_01"><measure type="articulationRate" articulationRate="5.342279799378205"/></measures><measures speechEventID="FOLK_E_00141_SE_01"><measure type="articulationRate" articulationRate="4.700073587010699"/></measures><measures speechEventID="FOLK_E_00142_SE_01"><measure type="articulationRate" articulationRate="4.906766398100803"/></measures><measures speechEventID="FOLK_E_00143_SE_01"><measure type="articulationRate" articulationRate="4.055706531256589"/></measures><measures speechEventID="FOLK_E_00144_SE_01"><measure type="articulationRate" articulationRate="6.432915170102207"/></measures><measures speechEventID="FOLK_E_00146_SE_01"><measure type="articulationRate" articulationRate="5.088441536575376"/></measures><measures speechEventID="FOLK_E_00147_SE_01"><measure type="articulationRate" articulationRate="4.3868128012772925"/></measures><measures speechEventID="FOLK_E_00148_SE_01"><measure type="articulationRate" articulationRate="4.72837756815951"/></measures><measures speechEventID="FOLK_E_00150_SE_01"><measure type="articulationRate" articulationRate="5.611383551732449"/></measures><measures speechEventID="FOLK_E_00151_SE_01"><measure type="articulationRate" articulationRate="4.734942223806031"/></measures><measures speechEventID="FOLK_E_00152_SE_01"><measure type="articulationRate" articulationRate="4.570476574846735"/></measures><measures speechEventID="FOLK_E_00153_SE_01"><measure type="articulationRate" articulationRate="4.692032076437467"/></measures><measures speechEventID="FOLK_E_00154_SE_01"><measure type="articulationRate" articulationRate="5.287009063444108"/></measures><measures speechEventID="FOLK_E_00155_SE_01"><measure type="articulationRate" articulationRate="5.198736509607789"/></measures><measures speechEventID="FOLK_E_00156_SE_01"><measure type="articulationRate" articulationRate="5.394466193351459"/></measures><measures speechEventID="FOLK_E_00157_SE_01"><measure type="articulationRate" articulationRate="4.587607808005874"/></measures><measures speechEventID="FOLK_E_00158_SE_01"><measure type="articulationRate" articulationRate="5.657894736842111"/></measures><measures speechEventID="FOLK_E_00159_SE_01"><measure type="articulationRate" articulationRate="5.328719723183388"/></measures><measures speechEventID="FOLK_E_00160_SE_01"><measure type="articulationRate" articulationRate="5.3270269803732395"/></measures><measures speechEventID="FOLK_E_00161_SE_01"><measure type="articulationRate" articulationRate="5.232670466236952"/></measures><measures speechEventID="FOLK_E_00162_SE_01"><measure type="articulationRate" articulationRate="5.280167690155775"/></measures><measures speechEventID="FOLK_E_00163_SE_01"><measure type="articulationRate" articulationRate="5.601840970976008"/></measures><measures speechEventID="FOLK_E_00165_SE_01"><measure type="articulationRate" articulationRate="5.57870659981201"/></measures><measures speechEventID="FOLK_E_00166_SE_01"><measure type="articulationRate" articulationRate="5.762641152772862"/></measures><measures speechEventID="FOLK_E_00167_SE_01"><measure type="articulationRate" articulationRate="5.213289154829131"/></measures><measures speechEventID="FOLK_E_00168_SE_01"><measure type="articulationRate" articulationRate="5.355811771091022"/></measures><measures speechEventID="FOLK_E_00169_SE_01"><measure type="articulationRate" articulationRate="5.201603167704894"/></measures><measures speechEventID="FOLK_E_00171_SE_01"><measure type="articulationRate" articulationRate="5.039949715335621"/></measures><measures speechEventID="FOLK_E_00172_SE_01"><measure type="articulationRate" articulationRate="5.151424086403007"/></measures><measures speechEventID="FOLK_E_00173_SE_01"><measure type="articulationRate" articulationRate="5.576580256498294"/></measures><measures speechEventID="FOLK_E_00174_SE_01"><measure type="articulationRate" articulationRate="5.795177344387815"/></measures><measures speechEventID="FOLK_E_00175_SE_01"><measure type="articulationRate" articulationRate="4.234356516640838"/></measures><measures speechEventID="FOLK_E_00176_SE_01"><measure type="articulationRate" articulationRate="4.750550276567246"/></measures><measures speechEventID="FOLK_E_00177_SE_01"><measure type="articulationRate" articulationRate="4.556872166006778"/></measures><measures speechEventID="FOLK_E_00178_SE_01"><measure type="articulationRate" articulationRate="4.627864210205677"/></measures><measures speechEventID="FOLK_E_00179_SE_01"><measure type="articulationRate" articulationRate="4.353262389733345"/></measures><measures speechEventID="FOLK_E_00180_SE_01"><measure type="articulationRate" articulationRate="5.124468884556839"/></measures><measures speechEventID="FOLK_E_00181_SE_01"><measure type="articulationRate" articulationRate="4.616316333590855"/></measures><measures speechEventID="FOLK_E_00182_SE_01"><measure type="articulationRate" articulationRate="4.758594140528506"/></measures><measures speechEventID="FOLK_E_00183_SE_01"><measure type="articulationRate" articulationRate="4.1837702977897955"/></measures><measures speechEventID="FOLK_E_00184_SE_01"><measure type="articulationRate" articulationRate="4.130884833614469"/></measures><measures speechEventID="FOLK_E_00185_SE_01"><measure type="articulationRate" articulationRate="3.9222366032038556"/></measures><measures speechEventID="FOLK_E_00186_SE_01"><measure type="articulationRate" articulationRate="4.594138554144788"/></measures><measures speechEventID="FOLK_E_00187_SE_01"><measure type="articulationRate" articulationRate="4.949884874727244"/></measures><measures speechEventID="FOLK_E_00188_SE_01"><measure type="articulationRate" articulationRate="4.124370197523886"/></measures><measures speechEventID="FOLK_E_00189_SE_01"><measure type="articulationRate" articulationRate="4.20718623581407"/></measures><measures speechEventID="FOLK_E_00190_SE_01"><measure type="articulationRate" articulationRate="5.380191937845052"/></measures><measures speechEventID="FOLK_E_00191_SE_01"><measure type="articulationRate" articulationRate="5.241788892045291"/></measures><measures speechEventID="FOLK_E_00193_SE_01"><measure type="articulationRate" articulationRate="4.193550274051927"/></measures><measures speechEventID="FOLK_E_00194_SE_01"><measure type="articulationRate" articulationRate="4.596491376681468"/></measures><measures speechEventID="FOLK_E_00197_SE_01"><measure type="articulationRate" articulationRate="5.748279676197378"/></measures><measures speechEventID="FOLK_E_00198_SE_01"><measure type="articulationRate" articulationRate="5.564611219759204"/></measures><measures speechEventID="FOLK_E_00201_SE_01"><measure type="articulationRate" articulationRate="4.72372590066499"/></measures><measures speechEventID="FOLK_E_00202_SE_01"><measure type="articulationRate" articulationRate="5.435992925931102"/></measures><measures speechEventID="FOLK_E_00203_SE_01"><measure type="articulationRate" articulationRate="4.179817928869644"/></measures><measures speechEventID="FOLK_E_00204_SE_01"><measure type="articulationRate" articulationRate="5.195638362808118"/></measures><measures speechEventID="FOLK_E_00206_SE_01"><measure type="articulationRate" articulationRate="5.338621547021941"/></measures><measures speechEventID="FOLK_E_00207_SE_01"><measure type="articulationRate" articulationRate="4.406576172267648"/></measures><measures speechEventID="FOLK_E_00208_SE_01"><measure type="articulationRate" articulationRate="4.6475600309837475"/></measures><measures speechEventID="FOLK_E_00209_SE_01"><measure type="articulationRate" articulationRate="4.110270321289011"/></measures><measures speechEventID="FOLK_E_00210_SE_01"><measure type="articulationRate" articulationRate="4.459733625267507"/></measures><measures speechEventID="FOLK_E_00211_SE_01"><measure type="articulationRate" articulationRate="5.089579674451228"/></measures><measures speechEventID="FOLK_E_00212_SE_01"><measure type="articulationRate" articulationRate="5.055439908237393"/></measures><measures speechEventID="FOLK_E_00213_SE_01"><measure type="articulationRate" articulationRate="5.020256976831863"/></measures><measures speechEventID="FOLK_E_00214_SE_01"><measure type="articulationRate" articulationRate="5.532503457814661"/></measures><measures speechEventID="FOLK_E_00215_SE_01"><measure type="articulationRate" articulationRate="5.323169233194687"/></measures><measures speechEventID="FOLK_E_00216_SE_01"><measure type="articulationRate" articulationRate="5.327309708597159"/></measures><measures speechEventID="FOLK_E_00217_SE_01"><measure type="articulationRate" articulationRate="5.275460707853555"/></measures><measures speechEventID="FOLK_E_00218_SE_01"><measure type="articulationRate" articulationRate="5.061130131933423"/></measures><measures speechEventID="FOLK_E_00219_SE_01"><measure type="articulationRate" articulationRate="4.366342516796656"/></measures><measures speechEventID="FOLK_E_00220_SE_01"><measure type="articulationRate" articulationRate="5.76123318849772"/></measures><measures speechEventID="FOLK_E_00221_SE_01"><measure type="articulationRate" articulationRate="5.200792697327215"/></measures><measures speechEventID="FOLK_E_00223_SE_01"><measure type="articulationRate" articulationRate="5.662974076664486"/></measures><measures speechEventID="FOLK_E_00224_SE_01"><measure type="articulationRate" articulationRate="5.671677958719867"/></measures><measures speechEventID="FOLK_E_00225_SE_01"><measure type="articulationRate" articulationRate="5.053059785748961"/></measures><measures speechEventID="FOLK_E_00226_SE_01"><measure type="articulationRate" articulationRate="5.068223491853704"/></measures><measures speechEventID="FOLK_E_00227_SE_01"><measure type="articulationRate" articulationRate="5.287319313639628"/></measures><measures speechEventID="FOLK_E_00228_SE_01"><measure type="articulationRate" articulationRate="5.0786227648023905"/></measures><measures speechEventID="FOLK_E_00229_SE_01"><measure type="articulationRate" articulationRate="5.273405808859323"/></measures><measures speechEventID="FOLK_E_00230_SE_01"><measure type="articulationRate" articulationRate="4.59100442787229"/></measures><measures speechEventID="FOLK_E_00231_SE_01"><measure type="articulationRate" articulationRate="5.647930068782885"/></measures><measures speechEventID="FOLK_E_00235_SE_01"><measure type="articulationRate" articulationRate="5.6167153448663205"/></measures><measures speechEventID="FOLK_E_00237_SE_01"><measure type="articulationRate" articulationRate="5.569418105599364"/></measures><measures speechEventID="FOLK_E_00238_SE_01"><measure type="articulationRate" articulationRate="5.684066625894881"/></measures><measures speechEventID="FOLK_E_00239_SE_01"><measure type="articulationRate" articulationRate="4.160782731490823"/></measures><measures speechEventID="FOLK_E_00243_SE_01"><measure type="articulationRate" articulationRate="5.448880687689043"/></measures><measures speechEventID="FOLK_E_00246_SE_01"><measure type="articulationRate" articulationRate="5.445926913116568"/></measures><measures speechEventID="FOLK_E_00248_SE_01"><measure type="articulationRate" articulationRate="4.9670448152485225"/></measures><measures speechEventID="FOLK_E_00250_SE_01"><measure type="articulationRate" articulationRate="5.121383438643144"/></measures><measures speechEventID="FOLK_E_00251_SE_01"><measure type="articulationRate" articulationRate="4.799509351792869"/></measures><measures speechEventID="FOLK_E_00252_SE_01"><measure type="articulationRate" articulationRate="5.065185302353845"/></measures><measures speechEventID="FOLK_E_00253_SE_01"><measure type="articulationRate" articulationRate="5.539318320693012"/></measures><measures speechEventID="FOLK_E_00254_SE_01"><measure type="articulationRate" articulationRate="5.000205018938814"/></measures><measures speechEventID="FOLK_E_00255_SE_01"><measure type="articulationRate" articulationRate="5.012397400820787"/></measures><measures speechEventID="FOLK_E_00256_SE_01"><measure type="articulationRate" articulationRate="4.701024347932652"/></measures><measures speechEventID="FOLK_E_00257_SE_01"><measure type="articulationRate" articulationRate="4.469908269515402"/></measures><measures speechEventID="FOLK_E_00258_SE_01"><measure type="articulationRate" articulationRate="5.284254274956758"/></measures><measures speechEventID="FOLK_E_00259_SE_01"><measure type="articulationRate" articulationRate="5.015724471738274"/></measures><measures speechEventID="FOLK_E_00260_SE_01"><measure type="articulationRate" articulationRate="5.390292005482633"/></measures><measures speechEventID="FOLK_E_00261_SE_01"><measure type="articulationRate" articulationRate="5.278545669658634"/></measures><measures speechEventID="FOLK_E_00262_SE_01"><measure type="articulationRate" articulationRate="4.990615150334672"/></measures><measures speechEventID="FOLK_E_00263_SE_01"><measure type="articulationRate" articulationRate="4.3320896209956565"/></measures><measures speechEventID="FOLK_E_00264_SE_01"><measure type="articulationRate" articulationRate="5.823771158854164"/></measures><measures speechEventID="FOLK_E_00265_SE_01"><measure type="articulationRate" articulationRate="4.293801015758775"/></measures><measures speechEventID="FOLK_E_00266_SE_01"><measure type="articulationRate" articulationRate="4.373017246390818"/></measures><measures speechEventID="FOLK_E_00267_SE_01"><measure type="articulationRate" articulationRate="5.455667090546971"/></measures><measures speechEventID="FOLK_E_00268_SE_01"><measure type="articulationRate" articulationRate="5.254246014266845"/></measures><measures speechEventID="FOLK_E_00269_SE_01"><measure type="articulationRate" articulationRate="4.575306510197624"/></measures><measures speechEventID="FOLK_E_00270_SE_01"><measure type="articulationRate" articulationRate="5.193211461400546"/></measures><measures speechEventID="FOLK_E_00271_SE_01"><measure type="articulationRate" articulationRate="5.470368730202169"/></measures><measures speechEventID="FOLK_E_00272_SE_01"><measure type="articulationRate" articulationRate="5.870765129321349"/></measures><measures speechEventID="FOLK_E_00273_SE_01"><measure type="articulationRate" articulationRate="4.834070290867364"/></measures><measures speechEventID="FOLK_E_00274_SE_01"><measure type="articulationRate" articulationRate="4.873804783020135"/></measures><measures speechEventID="FOLK_E_00285_SE_01"><measure type="articulationRate" articulationRate="4.701356441045614"/></measures><measures speechEventID="FOLK_E_00286_SE_01"><measure type="articulationRate" articulationRate="4.174637254729063"/></measures><measures speechEventID="FOLK_E_00287_SE_01"><measure type="articulationRate" articulationRate="5.382361850174192"/></measures><measures speechEventID="FOLK_E_00288_SE_01"><measure type="articulationRate" articulationRate="5.054828666288236"/></measures><measures speechEventID="FOLK_E_00289_SE_01"><measure type="articulationRate" articulationRate="4.662110427360116"/></measures><measures speechEventID="FOLK_E_00290_SE_01"><measure type="articulationRate" articulationRate="5.109285620605108"/></measures><measures speechEventID="FOLK_E_00291_SE_01"><measure type="articulationRate" articulationRate="4.963958668589996"/></measures><measures speechEventID="FOLK_E_00292_SE_01"><measure type="articulationRate" articulationRate="4.723423347911197"/></measures><measures speechEventID="FOLK_E_00293_SE_01"><measure type="articulationRate" articulationRate="5.7644777038405"/></measures><measures speechEventID="FOLK_E_00294_SE_01"><measure type="articulationRate" articulationRate="4.495207222721697"/></measures><measures speechEventID="FOLK_E_00295_SE_01"><measure type="articulationRate" articulationRate="4.99942600380617"/></measures><measures speechEventID="FOLK_E_00296_SE_01"><measure type="articulationRate" articulationRate="4.362529696794926"/></measures><measures speechEventID="FOLK_E_00298_SE_01"><measure type="articulationRate" articulationRate="5.499066196306287"/></measures><measures speechEventID="FOLK_E_00299_SE_01"><measure type="articulationRate" articulationRate="4.994223261722001"/></measures><measures speechEventID="FOLK_E_00300_SE_01"><measure type="articulationRate" articulationRate="4.708015243972471"/></measures><measures speechEventID="FOLK_E_00301_SE_01"><measure type="articulationRate" articulationRate="5.0874750249992315"/></measures><measures speechEventID="FOLK_E_00302_SE_01"><measure type="articulationRate" articulationRate="5.915509715416014"/></measures><measures speechEventID="FOLK_E_00303_SE_01"><measure type="articulationRate" articulationRate="4.865524540453235"/></measures><measures speechEventID="FOLK_E_00304_SE_01"><measure type="articulationRate" articulationRate="5.30827640342901"/></measures><measures speechEventID="FOLK_E_00305_SE_01"><measure type="articulationRate" articulationRate="6.000850256712122"/></measures><measures speechEventID="FOLK_E_00308_SE_01"><measure type="articulationRate" articulationRate="4.402774238110586"/></measures><measures speechEventID="FOLK_E_00309_SE_01"><measure type="articulationRate" articulationRate="4.353145904063766"/></measures><measures speechEventID="FOLK_E_00311_SE_01"><measure type="articulationRate" articulationRate="5.034275858390906"/></measures><measures speechEventID="FOLK_E_00313_SE_01"><measure type="articulationRate" articulationRate="5.523614602441288"/></measures><measures speechEventID="FOLK_E_00315_SE_01"><measure type="articulationRate" articulationRate="4.268686675994634"/></measures><measures speechEventID="FOLK_E_00316_SE_01"><measure type="articulationRate" articulationRate="4.547647901496503"/></measures><measures speechEventID="FOLK_E_00317_SE_01"><measure type="articulationRate" articulationRate="5.60993227553242"/></measures><measures speechEventID="FOLK_E_00318_SE_01"><measure type="articulationRate" articulationRate="4.421781823826812"/></measures><measures speechEventID="FOLK_E_00319_SE_01"><measure type="articulationRate" articulationRate="4.760876852508283"/></measures><measures speechEventID="FOLK_E_00321_SE_01"><measure type="articulationRate" articulationRate="5.094419630236881"/></measures><measures speechEventID="FOLK_E_00322_SE_01"><measure type="articulationRate" articulationRate="4.21798141954899"/></measures><measures speechEventID="FOLK_E_00323_SE_01"><measure type="articulationRate" articulationRate="5.390584631713207"/></measures><measures speechEventID="FOLK_E_00324_SE_01"><measure type="articulationRate" articulationRate="5.34968366025844"/></measures><measures speechEventID="FOLK_E_00325_SE_01"><measure type="articulationRate" articulationRate="4.172263585746889"/></measures><measures speechEventID="FOLK_E_00327_SE_01"><measure type="articulationRate" articulationRate="4.615874278469773"/></measures><measures speechEventID="FOLK_E_00329_SE_01"><measure type="articulationRate" articulationRate="5.033559889736048"/></measures><measures speechEventID="FOLK_E_00330_SE_01"><measure type="articulationRate" articulationRate="4.7820322039853025"/></measures><measures speechEventID="FOLK_E_00331_SE_01"><measure type="articulationRate" articulationRate="5.3950773024199465"/></measures><measures speechEventID="FOLK_E_00332_SE_01"><measure type="articulationRate" articulationRate="5.02544438146723"/></measures><measures speechEventID="FOLK_E_00333_SE_01"><measure type="articulationRate" articulationRate="5.346410614673796"/></measures><measures speechEventID="FOLK_E_00334_SE_01"><measure type="articulationRate" articulationRate="4.144658265229618"/></measures><measures speechEventID="FOLK_E_00335_SE_01"><measure type="articulationRate" articulationRate="4.546221932807571"/></measures><measures speechEventID="FOLK_E_00337_SE_01"><measure type="articulationRate" articulationRate="4.838617810460782"/></measures><measures speechEventID="FOLK_E_00338_SE_01"><measure type="articulationRate" articulationRate="4.86805860777249"/></measures><measures speechEventID="FOLK_E_00339_SE_01"><measure type="articulationRate" articulationRate="4.435694498531935"/></measures><measures speechEventID="FOLK_E_00340_SE_01"><measure type="articulationRate" articulationRate="4.680983506514323"/></measures><measures speechEventID="FOLK_E_00342_SE_01"><measure type="articulationRate" articulationRate="4.251480165237928"/></measures><measures speechEventID="FOLK_E_00343_SE_01"><measure type="articulationRate" articulationRate="4.990677869534918"/></measures><measures speechEventID="FOLK_E_00344_SE_01"><measure type="articulationRate" articulationRate="4.771593389460574"/></measures><measures speechEventID="FOLK_E_00345_SE_01"><measure type="articulationRate" articulationRate="2.044734568493807"/></measures><measures speechEventID="FOLK_E_00346_SE_01"><measure type="articulationRate" articulationRate="5.520119134142799"/></measures><measures speechEventID="FOLK_E_00347_SE_01"><measure type="articulationRate" articulationRate="4.744840571048179"/></measures><measures speechEventID="FOLK_E_00348_SE_01"><measure type="articulationRate" articulationRate="4.953677634597265"/></measures><measures speechEventID="FOLK_E_00349_SE_01"><measure type="articulationRate" articulationRate="4.790779309080637"/></measures><measures speechEventID="FOLK_E_00350_SE_01"><measure type="articulationRate" articulationRate="4.788424076553425"/></measures><measures speechEventID="FOLK_E_00351_SE_01"><measure type="articulationRate" articulationRate="4.945013959187702"/></measures><measures speechEventID="FOLK_E_00352_SE_01"><measure type="articulationRate" articulationRate="5.565454878515882"/></measures><measures speechEventID="FOLK_E_00353_SE_01"><measure type="articulationRate" articulationRate="4.562850789819562"/></measures><measures speechEventID="FOLK_E_00354_SE_01"><measure type="articulationRate" articulationRate="5.37588635939543"/></measures><measures speechEventID="FOLK_E_00355_SE_01"><measure type="articulationRate" articulationRate="5.036430531879194"/></measures><measures speechEventID="FOLK_E_00356_SE_01"><measure type="articulationRate" articulationRate="4.194972890797357"/></measures><measures speechEventID="FOLK_E_00357_SE_01"><measure type="articulationRate" articulationRate="3.7195635634351523"/></measures><measures speechEventID="FOLK_E_00358_SE_01"><measure type="articulationRate" articulationRate="4.772693740049438"/></measures><measures speechEventID="FOLK_E_00359_SE_01"><measure type="articulationRate" articulationRate="4.240203949222433"/></measures><measures speechEventID="FOLK_E_00360_SE_01"><measure type="articulationRate" articulationRate="4.34110143348893"/></measures><measures speechEventID="FOLK_E_00361_SE_01"><measure type="articulationRate" articulationRate="4.648437854873326"/></measures><measures speechEventID="FOLK_E_00362_SE_01"><measure type="articulationRate" articulationRate="4.346976043794218"/></measures><measures speechEventID="FOLK_E_00363_SE_01"><measure type="articulationRate" articulationRate="4.365756756348472"/></measures><measures speechEventID="FOLK_E_00364_SE_01"><measure type="articulationRate" articulationRate="3.97371175945587"/></measures><measures speechEventID="FOLK_E_00365_SE_01"><measure type="articulationRate" articulationRate="4.770423375074546"/></measures><measures speechEventID="FOLK_E_00366_SE_01"><measure type="articulationRate" articulationRate="4.2635044023161734"/></measures><measures speechEventID="FOLK_E_00367_SE_01"><measure type="articulationRate" articulationRate="4.988827105960608"/></measures><measures speechEventID="FOLK_E_00368_SE_01"><measure type="articulationRate" articulationRate="5.189961101934251"/></measures><measures speechEventID="FOLK_E_00370_SE_01"><measure type="articulationRate" articulationRate="4.30671054880898"/></measures><measures speechEventID="FOLK_E_00371_SE_01"><measure type="articulationRate" articulationRate="4.635629548399957"/></measures><measures speechEventID="FOLK_E_00372_SE_01"><measure type="articulationRate" articulationRate="5.298714350443117"/></measures><measures speechEventID="FOLK_E_00373_SE_01"><measure type="articulationRate" articulationRate="5.313953248751547"/></measures><measures speechEventID="FOLK_E_00374_SE_01"><measure type="articulationRate" articulationRate="5.155573095586157"/></measures><measures speechEventID="FOLK_E_00375_SE_01"><measure type="articulationRate" articulationRate="5.467464323274553"/></measures><measures speechEventID="FOLK_E_00376_SE_01"><measure type="articulationRate" articulationRate="5.23653697600664"/></measures><measures speechEventID="FOLK_E_00377_SE_01"><measure type="articulationRate" articulationRate="4.615455896556761"/></measures><measures speechEventID="FOLK_E_00378_SE_01"><measure type="articulationRate" articulationRate="3.9285175252226106"/></measures><measures speechEventID="FOLK_E_00379_SE_01"><measure type="articulationRate" articulationRate="3.139464889885222"/></measures><measures speechEventID="FOLK_E_00380_SE_01"><measure type="articulationRate" articulationRate="4.636511452006645"/></measures><measures speechEventID="FOLK_E_00382_SE_01"><measure type="articulationRate" articulationRate="5.119672597237746"/></measures><measures speechEventID="FOLK_E_00383_SE_01"><measure type="articulationRate" articulationRate="3.990736583157148"/></measures><measures speechEventID="FOLK_E_00384_SE_01"><measure type="articulationRate" articulationRate="4.0699861686232275"/></measures><measures speechEventID="FOLK_E_00385_SE_01"><measure type="articulationRate" articulationRate="4.0902708831460375"/></measures><measures speechEventID="FOLK_E_00386_SE_01"><measure type="articulationRate" articulationRate="5.035331771054623"/></measures><measures speechEventID="FOLK_E_00387_SE_01"><measure type="articulationRate" articulationRate="5.041184065265788"/></measures><measures speechEventID="FOLK_E_00388_SE_01"><measure type="articulationRate" articulationRate="4.9198324431312805"/></measures><measures speechEventID="FOLK_E_00389_SE_01"><measure type="articulationRate" articulationRate="4.9380408412906265"/></measures><measures speechEventID="FOLK_E_00390_SE_01"><measure type="articulationRate" articulationRate="5.023399828748586"/></measures><measures speechEventID="FOLK_E_00391_SE_01"><measure type="articulationRate" articulationRate="5.0309618230693385"/></measures><measures speechEventID="FOLK_E_00392_SE_01"><measure type="articulationRate" articulationRate="4.7008041203609805"/></measures><measures speechEventID="FOLK_E_00393_SE_01"><measure type="articulationRate" articulationRate="4.357454416907458"/></measures><measures speechEventID="FOLK_E_00394_SE_01"><measure type="articulationRate" articulationRate="4.988811781161405"/></measures><measures speechEventID="FOLK_E_00395_SE_01"><measure type="articulationRate" articulationRate="3.8575247511038633"/></measures><measures speechEventID="FOLK_E_00396_SE_01"><measure type="articulationRate" articulationRate="4.3980966780806705"/></measures><measures speechEventID="FOLK_E_00397_SE_01"><measure type="articulationRate" articulationRate="5.087923831730306"/></measures><measures speechEventID="FOLK_E_00398_SE_01"><measure type="articulationRate" articulationRate="5.3096801443766255"/></measures><measures speechEventID="FOLK_E_00400_SE_01"><measure type="articulationRate" articulationRate="4.951886381955786"/></measures><measures speechEventID="FOLK_E_00401_SE_01"><measure type="articulationRate" articulationRate="4.381153518901161"/></measures><measures speechEventID="FOLK_E_00402_SE_01"><measure type="articulationRate" articulationRate="4.704843027956442"/></measures><measures speechEventID="FOLK_E_00403_SE_01"><measure type="articulationRate" articulationRate="4.5814088666855275"/></measures><measures speechEventID="FOLK_E_00404_SE_01"><measure type="articulationRate" articulationRate="4.503059855352305"/></measures><measures speechEventID="FOLK_E_00405_SE_01"><measure type="articulationRate" articulationRate="5.452038342637294"/></measures><measures speechEventID="FOLK_E_00406_SE_01"><measure type="articulationRate" articulationRate="4.491485801973885"/></measures><measures speechEventID="FOLK_E_00407_SE_01"><measure type="articulationRate" articulationRate="4.038884310038742"/></measures><measures speechEventID="FOLK_E_00408_SE_01"><measure type="articulationRate" articulationRate="4.427629596665605"/></measures><measures speechEventID="FOLK_E_00409_SE_01"><measure type="articulationRate" articulationRate="4.905855008004508"/></measures><measures speechEventID="FOLK_E_00410_SE_01"><measure type="articulationRate" articulationRate="4.864165556133752"/></measures><measures speechEventID="FOLK_E_00411_SE_01"><measure type="articulationRate" articulationRate="4.644063263049069"/></measures><measures speechEventID="FOLK_E_00412_SE_01"><measure type="articulationRate" articulationRate="5.0124025717604805"/></measures><measures speechEventID="FOLK_E_00413_SE_01"><measure type="articulationRate" articulationRate="3.039614649946022"/></measures><measures speechEventID="FOLK_E_00414_SE_01"><measure type="articulationRate" articulationRate="4.171252949675114"/></measures><measures speechEventID="FOLK_E_00415_SE_01"><measure type="articulationRate" articulationRate="5.2253610501887575"/></measures><measures speechEventID="FOLK_E_00416_SE_01"><measure type="articulationRate" articulationRate="4.8963119772866674"/></measures><measures speechEventID="FOLK_E_00417_SE_01"><measure type="articulationRate" articulationRate="4.800174336277551"/></measures><measures speechEventID="FOLK_E_00418_SE_01"><measure type="articulationRate" articulationRate="4.418033079326152"/></measures><measures speechEventID="FOLK_E_00419_SE_01"><measure type="articulationRate" articulationRate="4.952956308941305"/></measures><measures speechEventID="FOLK_E_00420_SE_01"><measure type="articulationRate" articulationRate="4.643471835747403"/></measures><measures speechEventID="FOLK_E_00421_SE_01"><measure type="articulationRate" articulationRate="3.8125515222990476"/></measures><measures speechEventID="FOLK_E_00422_SE_01"><measure type="articulationRate" articulationRate="4.455876498816693"/></measures><measures speechEventID="FOLK_E_00423_SE_01"><measure type="articulationRate" articulationRate="4.557699358073731"/></measures><measures speechEventID="FOLK_E_00424_SE_01"><measure type="articulationRate" articulationRate="2.830521372756461"/></measures><measures speechEventID="FOLK_E_00425_SE_01"><measure type="articulationRate" articulationRate="4.681026142620381"/></measures><measures speechEventID="FOLK_E_00426_SE_01"><measure type="articulationRate" articulationRate="4.597189950624458"/></measures><measures speechEventID="FOLK_E_00427_SE_01"><measure type="articulationRate" articulationRate="4.70473216646134"/></measures><measures speechEventID="FOLK_E_00428_SE_01"><measure type="articulationRate" articulationRate="5.16468690548644"/></measures><measures speechEventID="FOLK_E_00429_SE_01"><measure type="articulationRate" articulationRate="4.621459242974923"/></measures><measures speechEventID="FOLK_E_00430_SE_01"><measure type="articulationRate" articulationRate="3.8049803293215407"/></measures><measures speechEventID="FOLK_E_00431_SE_01"><measure type="articulationRate" articulationRate="3.7524825199709433"/></measures><measures speechEventID="FOLK_E_00432_SE_01"><measure type="articulationRate" articulationRate="4.807049234833952"/></measures><measures speechEventID="FOLK_E_00433_SE_01"><measure type="articulationRate" articulationRate="5.1528704029403976"/></measures><measures speechEventID="FOLK_E_00434_SE_01"><measure type="articulationRate" articulationRate="4.906548832157025"/></measures><measures speechEventID="FOLK_E_00435_SE_01"><measure type="articulationRate" articulationRate="5.246288670033544"/></measures><measures speechEventID="FOLK_E_00436_SE_01"><measure type="articulationRate" articulationRate="4.238950034456706"/></measures><measures speechEventID="FOLK_E_00437_SE_01"><measure type="articulationRate" articulationRate="5.554327018384451"/></measures><measures speechEventID="FOLK_E_00438_SE_01"><measure type="articulationRate" articulationRate="3.9929819619668963"/></measures><measures speechEventID="FOLK_E_00439_SE_01"><measure type="articulationRate" articulationRate="4.91362593843159"/></measures><measures speechEventID="FOLK_E_00440_SE_01"><measure type="articulationRate" articulationRate="4.246090628923639"/></measures><measures speechEventID="FOLK_E_00442_SE_01"><measure type="articulationRate" articulationRate="5.219614849674142"/></measures><measures speechEventID="FOLK_E_00443_SE_01"><measure type="articulationRate" articulationRate="5.319846556959977"/></measures><measures speechEventID="FOLK_E_00444_SE_01"><measure type="articulationRate" articulationRate="4.126991873065348"/></measures><measures speechEventID="FOLK_E_00445_SE_01"><measure type="articulationRate" articulationRate="4.109081167079835"/></measures><measures speechEventID="FOLK_E_00446_SE_01"><measure type="articulationRate" articulationRate="4.492601096266006"/></measures><measures speechEventID="FOLK_E_00447_SE_01"><measure type="articulationRate" articulationRate="4.962560875546199"/></measures><measures speechEventID="FOLK_E_00448_SE_01"><measure type="articulationRate" articulationRate="5.0697868133058925"/></measures><measures speechEventID="FOLK_E_00449_SE_01"><measure type="articulationRate" articulationRate="5.510746160791974"/></measures><measures speechEventID="FOLK_E_00450_SE_01"><measure type="articulationRate" articulationRate="4.5062807782031005"/></measures><measures speechEventID="FOLK_E_00451_SE_01"><measure type="articulationRate" articulationRate="4.624025736611611"/></measures><measures speechEventID="FOLK_E_00452_SE_01"><measure type="articulationRate" articulationRate="4.720922269147353"/></measures><measures speechEventID="FOLK_E_00453_SE_01"><measure type="articulationRate" articulationRate="4.487891253625778"/></measures><measures speechEventID="FOLK_E_00454_SE_01"><measure type="articulationRate" articulationRate="4.140424909914775"/></measures><measures speechEventID="FOLK_E_00455_SE_01"><measure type="articulationRate" articulationRate="4.383247647004773"/></measures><measures speechEventID="FOLK_E_00456_SE_01"><measure type="articulationRate" articulationRate="4.513416056070039"/></measures><measures speechEventID="FOLK_E_00457_SE_01"><measure type="articulationRate" articulationRate="4.417783919131761"/></measures><measures speechEventID="FOLK_E_00458_SE_01"><measure type="articulationRate" articulationRate="4.580232976868224"/></measures><measures speechEventID="FOLK_E_00459_SE_01"><measure type="articulationRate" articulationRate="4.890920104344608"/></measures><measures speechEventID="FOLK_E_00460_SE_01"><measure type="articulationRate" articulationRate="4.4101959125772785"/></measures><measures speechEventID="FOLK_E_00461_SE_01"><measure type="articulationRate" articulationRate="4.527111296094437"/></measures><measures speechEventID="FOLK_E_00462_SE_01"><measure type="articulationRate" articulationRate="4.853617848860804"/></measures><measures speechEventID="FOLK_E_00463_SE_01"><measure type="articulationRate" articulationRate="4.833696307884201"/></measures><measures speechEventID="FOLK_E_00464_SE_01"><measure type="articulationRate" articulationRate="4.4410919662002355"/></measures><measures speechEventID="FOLK_E_00472_SE_01"><measure type="articulationRate" articulationRate="4.5843119520343265"/></measures><measures speechEventID="FOLK_E_00473_SE_01"><measure type="articulationRate" articulationRate="5.390937802652085"/></measures><measures speechEventID="FOLK_E_00474_SE_01"><measure type="articulationRate" articulationRate="5.076836065756424"/></measures><measures speechEventID="FOLK_E_00475_SE_01"><measure type="articulationRate" articulationRate="4.685846888514569"/></measures><measures speechEventID="FOLK_E_00476_SE_01"><measure type="articulationRate" articulationRate="4.53532897074713"/></measures><measures speechEventID="FOLK_E_00477_SE_01"><measure type="articulationRate" articulationRate="5.055649743002827"/></measures><measures speechEventID="FOLK_E_00478_SE_01"><measure type="articulationRate" articulationRate="4.498067335310628"/></measures><measures speechEventID="FOLK_E_00485_SE_01"><measure type="articulationRate" articulationRate="4.589884498264375"/></measures><measures speechEventID="FOLK_E_00488_SE_01"><measure type="articulationRate" articulationRate="4.445722579775028"/></measures><measures speechEventID="FOLK_E_00489_SE_01"><measure type="articulationRate" articulationRate="4.854745705599296"/></measures><measures speechEventID="FOLK_E_00490_SE_01"><measure type="articulationRate" articulationRate="4.858269530110099"/></measures><measures speechEventID="FOLK_E_00491_SE_01"><measure type="articulationRate" articulationRate="5.473182202056664"/></measures><measures speechEventID="FOLK_E_00492_SE_01"><measure type="articulationRate" articulationRate="5.0684948178115405"/></measures></measures-document>